multiplier_16_bit.v
module multiplier_16bit (
    output reg [31:0] product,
    input [15:0] a,
    input [15:0] b,
    input clk,
    input start,
    input reset
);

reg [15:0] a_reg, b_reg;
reg [31:0] product_reg;
reg [4:0] count; // Needs to count up to 16
reg running;

always @(posedge clk or posedge reset) begin
    if (reset) begin
        product_reg <= 0;
        a_reg <= 0;
        b_reg <= 0;
        count <= 0;
        product <= 0;
        running <= 0;
    end else if (start && !running) begin
        a_reg <= a;
        b_reg <= b;
        product_reg <= 0;
        count <= 16;
        running <= 1;
    end else if (running) begin
        if (count > 0) begin
            if (b_reg[0] == 1) begin
                product_reg <= product_reg + (a_reg << (16 - count));
            end
            b_reg <= b_reg >> 1;
            count <= count - 1;
        end else begin
            product <= product_reg;
            running <= 0;
        end
    end
end

endmodule

tb_multiplier_16bit.v
`include "multiplier_16_bit.v"
`timescale 1ns / 1ps

module tb_multiplier_16bit;

reg [15:0] a;
reg [15:0] b;
reg clk;
reg start;
reg reset;
wire [31:0] product;

// Instantiation of UUT
multiplier_16bit uut (
    .product(product),
    .a(a),
    .b(b),
    .clk(clk),
    .start(start),
    .reset(reset)
);

// Clock generation of time period 10ns
initial begin
    clk = 0;
    forever #5 clk = ~clk; 
end

// Test sequence
initial begin
    a = 0;
    b = 0;
    start = 0;
    reset = 0;

    // Dump waveforms
    $dumpfile("multiplier_16bit_tb.vcd");
    $dumpvars(0, tb_multiplier_16bit);

    // Apply reset
    reset = 1;
    #20;
    reset = 0;

    // Test Case 1
    a = 16'd10; 
    b = 16'd20;
    start = 1;
    #10;
    start = 0;
    #320; // Intezaar

    $display("Test Case 1: 10 * 20");
    $display("Product: %d", product);

    // Firse reset
    reset = 1;
    #20;
    reset = 0;

    // Test Case 2
    a = 16'd100;
    b = 16'd25;
    start = 1;
    #10;
    start = 0;
    #320; // Intezaar

    $display("Test Case 2: 100 * 25");
    $display("Product: %d", product);

    // Firse reset
    reset = 1;
    #20;
    reset = 0;

    // Test Case 3
    a = 16'd1234;
    b = 16'd5678;
    start = 1;
    #10;
    start = 0;
    #320; // Intezaar

    $display("Test Case 3: 1234 * 5678");
    $display("Product: %d", product);

    // End simulation
    $finish;
end

endmodule

multiplier_16bit_tb.vcd
$date
	Mon Jul 22 11:41:43 2024
$end
$version
	Icarus Verilog
$end
$timescale
	1ps
$end
$scope module tb_multiplier_16bit $end
$var wire 32 ! product [31:0] $end
$var reg 16 " a [15:0] $end
$var reg 16 # b [15:0] $end
$var reg 1 $ clk $end
$var reg 1 % reset $end
$var reg 1 & start $end
$scope module uut $end
$var wire 16 ' a [15:0] $end
$var wire 16 ( b [15:0] $end
$var wire 1 $ clk $end
$var wire 1 % reset $end
$var wire 1 & start $end
$var reg 16 ) a_reg [15:0] $end
$var reg 16 * b_reg [15:0] $end
$var reg 5 + count [4:0] $end
$var reg 32 , product [31:0] $end
$var reg 32 - product_reg [31:0] $end
$var reg 1 . running $end
$upscope $end
$upscope $end
$enddefinitions $end
#0
$dumpvars
0.
b0 -
b0 ,
b0 +
b0 *
b0 )
b0 (
b0 '
0&
1%
0$
b0 #
b0 "
b0 !
$end
#5000
1$
#10000
0$
#15000
1$
#20000
0$
1&
b10100 #
b10100 (
b1010 "
b1010 '
0%
#25000
1.
b10000 +
b10100 *
b1010 )
1$
#30000
0$
0&
#35000
b1111 +
b1010 *
1$
#40000
0$
#45000
b1110 +
b101 *
1$
#50000
0$
#55000
b1101 +
b10 *
b101000 -
1$
#60000
0$
#65000
b1100 +
b1 *
1$
#70000
0$
#75000
b1011 +
b0 *
b11001000 -
1$
#80000
0$
#85000
b1010 +
1$
#90000
0$
#95000
b1001 +
1$
#100000
0$
#105000
b1000 +
1$
#110000
0$
#115000
b111 +
1$
#120000
0$
#125000
b110 +
1$
#130000
0$
#135000
b101 +
1$
#140000
0$
#145000
b100 +
1$
#150000
0$
#155000
b11 +
1$
#160000
0$
#165000
b10 +
1$
#170000
0$
#175000
b1 +
1$
#180000
0$
#185000
b0 +
1$
#190000
0$
#195000
0.
b11001000 !
b11001000 ,
1$
#200000
0$
#205000
1$
#210000
0$
#215000
1$
#220000
0$
#225000
1$
#230000
0$
#235000
1$
#240000
0$
#245000
1$
#250000
0$
#255000
1$
#260000
0$
#265000
1$
#270000
0$
#275000
1$
#280000
0$
#285000
1$
#290000
0$
#295000
1$
#300000
0$
#305000
1$
#310000
0$
#315000
1$
#320000
0$
#325000
1$
#330000
0$
#335000
1$
#340000
0$
#345000
1$
#350000
b0 !
b0 ,
b0 )
b0 -
0$
1%
#355000
1$
#360000
0$
#365000
1$
#370000
0$
1&
b11001 #
b11001 (
b1100100 "
b1100100 '
0%
#375000
1.
b10000 +
b11001 *
b1100100 )
1$
#380000
0$
0&
#385000
b1111 +
b1100 *
b1100100 -
1$
#390000
0$
#395000
b1110 +
b110 *
1$
#400000
0$
#405000
b1101 +
b11 *
1$
#410000
0$
#415000
b1100 +
b1 *
b1110000100 -
1$
#420000
0$
#425000
b1011 +
b0 *
b100111000100 -
1$
#430000
0$
#435000
b1010 +
1$
#440000
0$
#445000
b1001 +
1$
#450000
0$
#455000
b1000 +
1$
#460000
0$
#465000
b111 +
1$
#470000
0$
#475000
b110 +
1$
#480000
0$
#485000
b101 +
1$
#490000
0$
#495000
b100 +
1$
#500000
0$
#505000
b11 +
1$
#510000
0$
#515000
b10 +
1$
#520000
0$
#525000
b1 +
1$
#530000
0$
#535000
b0 +
1$
#540000
0$
#545000
0.
b100111000100 !
b100111000100 ,
1$
#550000
0$
#555000
1$
#560000
0$
#565000
1$
#570000
0$
#575000
1$
#580000
0$
#585000
1$
#590000
0$
#595000
1$
#600000
0$
#605000
1$
#610000
0$
#615000
1$
#620000
0$
#625000
1$
#630000
0$
#635000
1$
#640000
0$
#645000
1$
#650000
0$
#655000
1$
#660000
0$
#665000
1$
#670000
0$
#675000
1$
#680000
0$
#685000
1$
#690000
0$
#695000
1$
#700000
b0 !
b0 ,
b0 )
b0 -
0$
1%
#705000
1$
#710000
0$
#715000
1$
#720000
0$
1&
b1011000101110 #
b1011000101110 (
b10011010010 "
b10011010010 '
0%
#725000
1.
b10000 +
b1011000101110 *
b10011010010 )
1$
#730000
0$
0&
#735000
b1111 +
b101100010111 *
1$
#740000
0$
#745000
b1110 +
b10110001011 *
b100110100100 -
1$
#750000
0$
#755000
b1101 +
b1011000101 *
b1110011101100 -
1$
#760000
0$
#765000
b1100 +
b101100010 *
b100001101111100 -
1$
#770000
0$
#775000
b1011 +
b10110001 *
1$
#780000
0$
#785000
b1010 +
b1011000 *
b1101110110111100 -
1$
#790000
0$
#795000
b1001 +
b101100 *
1$
#800000
0$
#805000
b1000 +
b10110 *
1$
#810000
0$
#815000
b111 +
b1011 *
1$
#820000
0$
#825000
b110 +
b101 *
b10101000000110111100 -
1$
#830000
0$
#835000
b101 +
b10 *
b111011100100110111100 -
1$
#840000
0$
#845000
b100 +
b1 *
1$
#850000
0$
#855000
b11 +
b0 *
b11010101110100110111100 -
1$
#860000
0$
#865000
b10 +
1$
#870000
0$
#875000
b1 +
1$
#880000
0$
#885000
b0 +
1$
#890000
0$
#895000
0.
b11010101110100110111100 !
b11010101110100110111100 ,
1$
